{
  "type": "ars_nouveau:enchanting_apparatus",
  "keepNbtOfReagent": false,
  "pedestalItems": [
    {
      "tag": "c:storage_blocks/amethyst"
    },
    {
      "tag": "c:ingots/gold"
    },
    {
      "tag": "c:ingots/gold"
    }
  ],
  "reagent": {
    "item": "ars_nouveau:dominion_wand"
  },
  "result": {
    "count": 1,
    "id": "ars_additions:advanced_dominion_wand"
  },
  "sourceCost": 0,
  "neoforge:conditions": [
    {
      "type": "neoforge:mod_loaded",
      "modid": "ars_additions"
    }
  ]
}
