{
  "type": "minecraft:crafting_shaped",
  "category": "misc",
  "key": {
    "#": {
      "tag": "chipped:obsidian"
    },
    "A": {
      "tag": "forge:ingots/netherite"
    },
    "B": {
      "tag": "forge:books"
    },
    "T": {
      "item": "enchantinginfuser:enchanting_infuser"
    }
  },
  "pattern": [
    " B ",
    "A#A",
    "#T#"
  ],
  "result": {
    "item": "enchantinginfuser:advanced_enchanting_infuser"
  },
  "show_notification": true,
  "conditions": [
    {
      "type": "forge:mod_loaded",
      "modid": "enchantinginfuser"
    },
    {
      "type": "forge:mod_loaded",
      "modid": "chipped"
    }
  ]
}
