{
  "neoforge:conditions": [
    {
      "type": "neoforge:mod_loaded",
      "modid": "sophisticatedstorage"
    },
    {
      "type": "sophisticatedcore:item_enabled",
      "itemRegistryName": "sophisticatedstorage:iron_to_diamond_tier_upgrade"
    }
  ],
  "type": "minecraft:crafting_shaped",
  "category": "misc",
  "key": {
    "G": {
      "tag": "c:glass_blocks"
    },
    "D": {
      "tag": "c:gems/diamond"
    },
    "T": {
      "item": "sophisticatedstorage:iron_to_gold_tier_upgrade"
    },
    "g": {
      "tag": "c:gears/diamond"
    }
  },
  "pattern": [
    "GGG",
    "DTD",
    "GgG"
  ],
  "result": {
    "count": 1,
    "id": "sophisticatedstorage:iron_to_diamond_tier_upgrade"
  }
}
