{
  "type": "minecraft:crafting_shaped",
  "category": "redstone",
  "conditions": [
    {
      "type": "forge:mod_loaded",
      "modid": "jurassicreborn"
    }
  ],
  "key": {
    "A": {
      "item": "jurassicreborn:reinforced_stone_panel"
    },
    "B": {
      "tag": "monumental_recipes:tools/hammers"
    }
  },
  "pattern": [
    " A ",
    " A ",
    " B "
  ],
  "result": {
    "item": "jurassicreborn:reinforced_stone_panel_pressure_plate"
  }
},
"conditions": [
{
"type": "forge:mod_loaded",
"modid": "jurassicreborn"
}