{
  "type": "ars_nouveau:enchanting_apparatus",
  "keepNbtOfReagent": false,
  "output": {
    "id": "ars_elemental:air_upstream"
  },
  "pedestalItems": [
    {
      "item": "mysticalagriculture:air_essence"
    },
    {
      "item": "mysticalagriculture:air_essence"
    },
    {
      "item": "mysticalagriculture:air_essence"
    },
    {
      "item": "mysticalagriculture:air_essence"
    },
    {
      "item": "ars_nouveau:wilden_wing"
    },
    {
      "item": "minecraft:shulker_shell"
    },
    {
      "item": "minecraft:shulker_shell"
    }
  ],
  "reagent": [
    {
      "item": "minecraft:gold_block"
    }
  ],
  "sourceCost": 0,
  "neoforge:conditions": [
    {
      "type": "neoforge:mod_loaded",
      "modid": "ars_elemental"
    },
    {
      "type": "neoforge:mod_loaded",
      "modid": "ars_nouveau"
    },
    {
      "type": "neoforge:mod_loaded",
      "modid": "mysticalagriculture"
    }
  ]
}
