{
  "type": "minecraft:crafting_shaped",
  "key": {
    "C": {
      "tag": "minecraft:cauldrons"
    },
    "G": {
      "item": "reliquary:catalyzing_gland"
    },
    "I": {
      "item": "reliquary:infernal_claw"
    },
    "M": {
      "item": "reliquary:molten_core"
    },
    "N": {
      "item": "reliquary:nebulous_heart"
    }
  },
  "pattern": [
    "GNG",
    "ICI",
    "NMN"
  ],
  "result": {
    "id": "reliquary:apothecary_cauldron"
  },
  "neoforge:conditions": [
    {
      "type": "neoforge:mod_loaded",
      "modid": "reliquary"
    },
    {
      "type": "reliquary:potions_enabled"
    }
  ]
}
